{
  "updated_at": "2026-02-19T10:44:05.124888",
  "vehicle": {
    "year": 2024,
    "model": "Model Y Performance",
    "purchase_price": 54130.0,
    "net_cost": 46630.0,
    "previous_vehicle": "2016 Mazda CX-5 FWD Sport 2.5L"
  },
  "summary": {
    "total_charges": 31,
    "total_miles": 29695.0,
    "total_kwh": 7960.949999999999,
    "total_electricity_cost": 1145.8600000000004,
    "total_fuel_savings": 0,
    "avg_gas_equiv_mpg": 103.2,
    "breakeven": {
      "net_savings": -1667.9,
      "fuel_savings": 0,
      "maintenance_savings": 549.1,
      "insurance_cost": 2217.0,
      "breakeven_pct": -4.4,
      "months_remaining": null,
      "tesla_premium": 38030.0
    },
    "resale_value": 0
  },
  "ai_insight": "## Tesla Weekly Ownership Snapshot\n\n**Week in Review: Quiet Week \u2014 No Miles, No Charges Logged**\n\nLooks like the Model Y sat tight this week \u2014 zero miles, zero charges, and zero activity in the books, so there's not much to analyze on the efficiency front. What *is* worth noting is where things stand on the bigger picture: you're currently **-$1,667.90 net** on your break-even journey against that $38,030 Tesla premium, and with insurance costing you an extra **$2,217/year** ($119/month), every idle week is a small step backward since that clock keeps ticking regardless of miles driven. The bright side is that **$549.10 in cumulative maintenance savings** is already stacking up \u2014 oil changes, filters, and brake wear the CX-5 would've demanded by now \u2014 and your all-time efficiency of **103.2 MPGe** across nearly 30,000 miles shows the car earns its keep when it's moving. **This week's recommendation:** if the car was parked all week, double-check that you're not leaving it plugged in at a high state of charge for extended periods \u2014 keeping it between 20\u201380% SOC during storage weeks extends long-term battery health. Interesting footnote: your most recent Supercharger stop in Cleveland cost just **$5.23 for 15.41 kWh at $0.34/kWh** \u2014 that's actually one of your cheaper per-kWh SC sessions, suggesting off-peak timing is working in your favor on road trips.",
  "charge_history": [
    {
      "date": "2024-08-03",
      "miles": 29695.0,
      "kwh": 6978.2,
      "cost": 805.49,
      "gas_mpg": 103.2,
      "gas_price": 2.8,
      "savings": 1823.64,
      "soc_before": "",
      "soc_after": "",
      "temp": "",
      "charge_type": "historical_backfill"
    },
    {
      "date": "2024-08-04",
      "miles": 0,
      "kwh": 21.0,
      "cost": 8.19,
      "gas_mpg": 0,
      "gas_price": 0,
      "savings": 0,
      "soc_before": "",
      "soc_after": "",
      "temp": "",
      "charge_type": "supercharger"
    },
    {
      "date": "2024-08-05",
      "miles": 0,
      "kwh": 14.0,
      "cost": 5.46,
      "gas_mpg": 0,
      "gas_price": 0,
      "savings": 0,
      "soc_before": "",
      "soc_after": "",
      "temp": "",
      "charge_type": "supercharger"
    },
    {
      "date": "2024-08-09",
      "miles": 0,
      "kwh": 31.0,
      "cost": 12.09,
      "gas_mpg": 0,
      "gas_price": 0,
      "savings": 0,
      "soc_before": "",
      "soc_after": "",
      "temp": "",
      "charge_type": "supercharger"
    },
    {
      "date": "2024-08-21",
      "miles": 0,
      "kwh": 63.98,
      "cost": 15.99,
      "gas_mpg": 0,
      "gas_price": 0,
      "savings": 0,
      "soc_before": "",
      "soc_after": "",
      "temp": "",
      "charge_type": "supercharger"
    },
    {
      "date": "2024-08-21",
      "miles": 0,
      "kwh": 39.37,
      "cost": 15.35,
      "gas_mpg": 0,
      "gas_price": 0,
      "savings": 0,
      "soc_before": "",
      "soc_after": "",
      "temp": "",
      "charge_type": "supercharger"
    },
    {
      "date": "2024-08-22",
      "miles": 0,
      "kwh": 40.3,
      "cost": 15.71,
      "gas_mpg": 0,
      "gas_price": 0,
      "savings": 0,
      "soc_before": "",
      "soc_after": "",
      "temp": "",
      "charge_type": "supercharger"
    },
    {
      "date": "2024-08-23",
      "miles": 0,
      "kwh": 39.77,
      "cost": 15.51,
      "gas_mpg": 0,
      "gas_price": 0,
      "savings": 0,
      "soc_before": "",
      "soc_after": "",
      "temp": "",
      "charge_type": "supercharger"
    },
    {
      "date": "2024-08-25",
      "miles": 0,
      "kwh": 32.97,
      "cost": 11.86,
      "gas_mpg": 0,
      "gas_price": 0,
      "savings": 0,
      "soc_before": "",
      "soc_after": "",
      "temp": "",
      "charge_type": "supercharger"
    },
    {
      "date": "2024-08-25",
      "miles": 0,
      "kwh": 58.38,
      "cost": 14.59,
      "gas_mpg": 0,
      "gas_price": 0,
      "savings": 0,
      "soc_before": "",
      "soc_after": "",
      "temp": "",
      "charge_type": "supercharger"
    },
    {
      "date": "2024-08-25",
      "miles": 0,
      "kwh": 23.73,
      "cost": 7.35,
      "gas_mpg": 0,
      "gas_price": 0,
      "savings": 0,
      "soc_before": "",
      "soc_after": "",
      "temp": "",
      "charge_type": "supercharger"
    },
    {
      "date": "2024-08-28",
      "miles": 0,
      "kwh": 29.98,
      "cost": 11.69,
      "gas_mpg": 0,
      "gas_price": 0,
      "savings": 0,
      "soc_before": "",
      "soc_after": "",
      "temp": "",
      "charge_type": "supercharger"
    },
    {
      "date": "2024-12-22",
      "miles": 0,
      "kwh": 39.91,
      "cost": 13.96,
      "gas_mpg": 0,
      "gas_price": 0,
      "savings": 0,
      "soc_before": "",
      "soc_after": "",
      "temp": "",
      "charge_type": "supercharger"
    },
    {
      "date": "2024-12-22",
      "miles": 0,
      "kwh": 36.34,
      "cost": 14.17,
      "gas_mpg": 0,
      "gas_price": 0,
      "savings": 0,
      "soc_before": "",
      "soc_after": "",
      "temp": "",
      "charge_type": "supercharger"
    },
    {
      "date": "2024-12-22",
      "miles": 0,
      "kwh": 56.5,
      "cost": 20.34,
      "gas_mpg": 0,
      "gas_price": 0,
      "savings": 0,
      "soc_before": "",
      "soc_after": "",
      "temp": "",
      "charge_type": "supercharger"
    },
    {
      "date": "2024-12-22",
      "miles": 0,
      "kwh": 16.45,
      "cost": 6.41,
      "gas_mpg": 0,
      "gas_price": 0,
      "savings": 0,
      "soc_before": "",
      "soc_after": "",
      "temp": "",
      "charge_type": "supercharger"
    },
    {
      "date": "2024-12-22",
      "miles": 0,
      "kwh": 47.13,
      "cost": 16.49,
      "gas_mpg": 0,
      "gas_price": 0,
      "savings": 0,
      "soc_before": "",
      "soc_after": "",
      "temp": "",
      "charge_type": "supercharger"
    },
    {
      "date": "2025-05-09",
      "miles": 0,
      "kwh": 19.73,
      "cost": 5.91,
      "gas_mpg": 0,
      "gas_price": 0,
      "savings": 0,
      "soc_before": "",
      "soc_after": "",
      "temp": "",
      "charge_type": "supercharger"
    },
    {
      "date": "2025-05-09",
      "miles": 0,
      "kwh": 39.93,
      "cost": 13.29,
      "gas_mpg": 0,
      "gas_price": 0,
      "savings": 0,
      "soc_before": "",
      "soc_after": "",
      "temp": "",
      "charge_type": "supercharger"
    },
    {
      "date": "2025-05-09",
      "miles": 0,
      "kwh": 12.43,
      "cost": 4.22,
      "gas_mpg": 0,
      "gas_price": 0,
      "savings": 0,
      "soc_before": "",
      "soc_after": "",
      "temp": "",
      "charge_type": "supercharger"
    },
    {
      "date": "2025-05-09",
      "miles": 0,
      "kwh": 47.35,
      "cost": 17.99,
      "gas_mpg": 0,
      "gas_price": 0,
      "savings": 0,
      "soc_before": "",
      "soc_after": "",
      "temp": "",
      "charge_type": "supercharger"
    },
    {
      "date": "2025-05-12",
      "miles": 0,
      "kwh": 39.73,
      "cost": 15.09,
      "gas_mpg": 0,
      "gas_price": 0,
      "savings": 0,
      "soc_before": "",
      "soc_after": "",
      "temp": "",
      "charge_type": "supercharger"
    },
    {
      "date": "2025-05-12",
      "miles": 0,
      "kwh": 44.81,
      "cost": 15.23,
      "gas_mpg": 0,
      "gas_price": 0,
      "savings": 0,
      "soc_before": "",
      "soc_after": "",
      "temp": "",
      "charge_type": "supercharger"
    },
    {
      "date": "2025-05-12",
      "miles": 0,
      "kwh": 28.86,
      "cost": 10.1,
      "gas_mpg": 0,
      "gas_price": 0,
      "savings": 0,
      "soc_before": "",
      "soc_after": "",
      "temp": "",
      "charge_type": "supercharger"
    },
    {
      "date": "2025-05-12",
      "miles": 0,
      "kwh": 27.83,
      "cost": 9.46,
      "gas_mpg": 0,
      "gas_price": 0,
      "savings": 0,
      "soc_before": "",
      "soc_after": "",
      "temp": "",
      "charge_type": "supercharger"
    },
    {
      "date": "2025-05-17",
      "miles": 0,
      "kwh": 15.86,
      "cost": 5.39,
      "gas_mpg": 0,
      "gas_price": 0,
      "savings": 0,
      "soc_before": "",
      "soc_after": "",
      "temp": "",
      "charge_type": "supercharger"
    },
    {
      "date": "2025-05-17",
      "miles": 0,
      "kwh": 43.08,
      "cost": 13.78,
      "gas_mpg": 0,
      "gas_price": 0,
      "savings": 0,
      "soc_before": "",
      "soc_after": "",
      "temp": "",
      "charge_type": "supercharger"
    },
    {
      "date": "2025-05-18",
      "miles": 0,
      "kwh": 31.55,
      "cost": 10.72,
      "gas_mpg": 0,
      "gas_price": 0,
      "savings": 0,
      "soc_before": "",
      "soc_after": "",
      "temp": "",
      "charge_type": "supercharger"
    },
    {
      "date": "2025-06-06",
      "miles": 0,
      "kwh": 7.71,
      "cost": 2.62,
      "gas_mpg": 0,
      "gas_price": 0,
      "savings": 0,
      "soc_before": "",
      "soc_after": "",
      "temp": "",
      "charge_type": "supercharger"
    },
    {
      "date": "2025-09-07",
      "miles": 0,
      "kwh": 17.66,
      "cost": 6.18,
      "gas_mpg": 0,
      "gas_price": 0,
      "savings": 0,
      "soc_before": "",
      "soc_after": "",
      "temp": "",
      "charge_type": "supercharger"
    },
    {
      "date": "2025-12-19",
      "miles": 0,
      "kwh": 15.41,
      "cost": 5.23,
      "gas_mpg": 0,
      "gas_price": 0,
      "savings": 0,
      "soc_before": "",
      "soc_after": "",
      "temp": "",
      "charge_type": "supercharger"
    }
  ]
}